[
  {
    "ts": 1761822236117,
    "equity": 9889.86,
    "drawdown": 0.0
  },
  {
    "ts": 1761822250682,
    "equity": 9885.95,
    "drawdown": -0.04
  },
  {
    "ts": 1761822265252,
    "equity": 9885.93,
    "drawdown": -0.04
  },
  {
    "ts": 1761822279711,
    "equity": 9885.91,
    "drawdown": -0.04
  },
  {
    "ts": 1761822294942,
    "equity": 9885.89,
    "drawdown": -0.04
  },
  {
    "ts": 1761822310571,
    "equity": 9885.93,
    "drawdown": -0.04
  },
  {
    "ts": 1761822326483,
    "equity": 9885.94,
    "drawdown": -0.04
  },
  {
    "ts": 1761822341011,
    "equity": 9885.93,
    "drawdown": -0.04
  },
  {
    "ts": 1761822355773,
    "equity": 9885.96,
    "drawdown": -0.04
  },
  {
    "ts": 1761822370337,
    "equity": 9885.96,
    "drawdown": -0.04
  },
  {
    "ts": 1761822384880,
    "equity": 9886.01,
    "drawdown": -0.04
  },
  {
    "ts": 1761822399539,
    "equity": 9885.93,
    "drawdown": -0.04
  },
  {
    "ts": 1761822414316,
    "equity": 9885.85,
    "drawdown": -0.04
  },
  {
    "ts": 1761822428879,
    "equity": 9885.83,
    "drawdown": -0.04
  },
  {
    "ts": 1761822443495,
    "equity": 9885.83,
    "drawdown": -0.04
  },
  {
    "ts": 1761822458186,
    "equity": 9885.77,
    "drawdown": -0.04
  },
  {
    "ts": 1761822472994,
    "equity": 9885.84,
    "drawdown": -0.04
  },
  {
    "ts": 1761822487535,
    "equity": 9885.84,
    "drawdown": -0.04
  },
  {
    "ts": 1761822502934,
    "equity": 9885.79,
    "drawdown": -0.04
  },
  {
    "ts": 1761822518198,
    "equity": 9885.69,
    "drawdown": -0.04
  },
  {
    "ts": 1761822533647,
    "equity": 9885.64,
    "drawdown": -0.04
  }
]